[
  {
    "author": "Damp",
    "link": "https://www.ptt.cc/bbs/Gossiping/M.1641880145.A.104.html",
    "title": "[問卦] 尾牙表演歌舞  要取名什麼組?"
  },
  {
    "author": "soulmola",
    "link": "https://www.ptt.cc/bbs/Gossiping/M.1641880152.A.8E3.html",
    "title": "[問卦] 開F35和當醫生 哪個比較帥？"
  },
  {
    "author": "popgsct",
    "link": "https://www.ptt.cc/bbs/Gossiping/M.1641880199.A.F66.html",
    "title": "[新聞] 龐建國生前頭條號最後發文:台灣是中國的"
  },
  {
    "author": "MrTaxes",
    "link": "https://www.ptt.cc/bbs/Gossiping/M.1641880241.A.835.html",
    "title": "Re: [問卦] 為什麼是一直補助小黃啊"
  },
  {
    "author": "diebo",
    "link": "https://www.ptt.cc/bbs/Gossiping/M.1641880282.A.433.html",
    "title": "[新聞] Sandy主持「連犯致命錯誤」嚴重得罪老闆"
  },
  {
    "author": "fermilevel",
    "link": "https://www.ptt.cc/bbs/Gossiping/M.1641880382.A.3F1.html",
    "title": "Re: [新聞] 快訊／9:33洛杉磯返台！3救護車衝醫院　王必勝：確診者"
  },
  {
    "author": "ubcs",
    "link": "https://www.ptt.cc/bbs/Gossiping/M.1637425085.A.07D.html",
    "title": "[公告] 八卦板板規(2021.11.21)"
  },
  {
    "author": "cindy53964",
    "link": "https://www.ptt.cc/bbs/Gossiping/M.1641644688.A.35E.html",
    "title": "[協尋] 中壢民族路和環西路附近老人走失"
  },
  {
    "author": "guligula",
    "link": "https://www.ptt.cc/bbs/Gossiping/M.1641646455.A.5D3.html",
    "title": "[協尋] 5千台幣幫找一罐神秘豆瓣醬"
  },
  {
    "author": "resuscitate",
    "link": "https://www.ptt.cc/bbs/Gossiping/M.1641692422.A.ADC.html",
    "title": "[協尋] 三十萬/雲林斗南大埤，嘉義大林以北"
  },
  {
    "author": "kenscopen",
    "link": "https://www.ptt.cc/bbs/Gossiping/M.1641821669.A.AB7.html",
    "title": "[協尋] 1/9 10:40新北三芝淡金路中興路行車記錄器"
  },
  {
    "author": "fantazy00077",
    "link": "https://www.ptt.cc/bbs/Gossiping/M.1641879481.A.346.html",
    "title": "[問卦] 最經典的台灣鄉土劇是哪一部？"
  },
  {
    "author": "Gazooli",
    "link": "https://www.ptt.cc/bbs/Gossiping/M.1641879489.A.E53.html",
    "title": "[問卦] 吃到飽老闆賺什麼"
  },
  {
    "author": "aassdsd",
    "link": "https://www.ptt.cc/bbs/Gossiping/M.1641879503.A.667.html",
    "title": "[問卦] 孔子那輩的古人有戴眼鏡嗎？"
  },
  {
    "author": "lololol",
    "link": "https://www.ptt.cc/bbs/Gossiping/M.1641879554.A.4BC.html",
    "title": "[問卦] 木曜是否擋了傳統電視節目的盈利啊？"
  },
  {
    "author": "sx4152",
    "link": "https://www.ptt.cc/bbs/Gossiping/M.1641879671.A.560.html",
    "title": "[問卦] 肯德基為什麼可以這麼慢"
  },
  {
    "author": "poeta",
    "link": "https://www.ptt.cc/bbs/Gossiping/M.1641879701.A.C8B.html",
    "title": "[新聞] 堅定不移的鋼鐵支持！外交部：續助立陶宛"
  },
  {
    "author": "tth9955",
    "link": "https://www.ptt.cc/bbs/Gossiping/M.1641879712.A.53E.html",
    "title": "[問卦] 誤闖門派禁地驚見師叔被冰封住怎麼辦！"
  },
  {
    "author": "mcuronan",
    "link": "https://www.ptt.cc/bbs/Gossiping/M.1641879722.A.316.html",
    "title": "Re: [問卦] 政府打房能解決生育率的低迷嗎？"
  },
  {
    "author": "uhbygv45",
    "link": "https://www.ptt.cc/bbs/Gossiping/M.1641879757.A.DDB.html",
    "title": "Re: [問卦] 有沒有中國嚴重空污正要入侵台灣的八卦?"
  },
  {
    "author": "palajuice",
    "link": "https://www.ptt.cc/bbs/Gossiping/M.1641879867.A.75B.html",
    "title": "[新聞] 北市聯醫中興院區護理師驚傳確診 感染人"
  },
  {
    "author": "hahaman0204",
    "link": "https://www.ptt.cc/bbs/Gossiping/M.1641879873.A.721.html",
    "title": "[問卦] 公司是最後的防護網"
  },
  {
    "author": "disgusting",
    "link": "https://www.ptt.cc/bbs/Gossiping/M.1641879927.A.DD5.html",
    "title": "[問卦] 拜託…升三級吧…"
  },
  {
    "author": "energyaxd",
    "link": "https://www.ptt.cc/bbs/Gossiping/M.1641879933.A.F0A.html",
    "title": "[問卦] 希望Omicron進來的人是有問題嗎？"
  },
  {
    "author": "Workforme",
    "link": "https://www.ptt.cc/bbs/Gossiping/M.1641879971.A.008.html",
    "title": "[問卦] 喜歡畫大餅的都是些什麼人？"
  },
  {
    "author": "cores",
    "link": "https://www.ptt.cc/bbs/Gossiping/M.1641879985.A.8FC.html",
    "title": "[新聞] 成本大增政府卻不准漲價 卜蜂：獲利無法"
  },
  {
    "author": "SAgirl",
    "link": "https://www.ptt.cc/bbs/Gossiping/M.1641879987.A.EC4.html",
    "title": "[新聞] 最小確診者的哥哥也染疫！ 中壢某國小午"
  },
  {
    "author": "THEBUG",
    "link": "https://www.ptt.cc/bbs/Gossiping/M.1641879998.A.B47.html",
    "title": "Re: [新聞] 《木曜4》合作2天王破局爆內幕！看不上1"
  },
  {
    "author": "rick789j",
    "link": "https://www.ptt.cc/bbs/Gossiping/M.1641880020.A.B7E.html",
    "title": "[新聞] 土方公會理事長 亂倒廢土撈1.7億"
  },
  {
    "author": "callmeanswer",
    "link": "https://www.ptt.cc/bbs/Gossiping/M.1641880030.A.58A.html",
    "title": "Re: [新聞] 北市聯醫中興院區護理師驚傳確診 感染人"
  },
  {
    "author": "knight45683",
    "link": "https://www.ptt.cc/bbs/Gossiping/M.1641880138.A.08F.html",
    "title": "[新聞] 高一必修本土語？教部：學校若不開課要"
  },
  {
    "author": "hinoapple",
    "link": "https://www.ptt.cc/bbs/Gossiping/M.1641879026.A.2E6.html",
    "title": "[問卦] 現在的流量密碼是不是三個女生？"
  },
  {
    "author": "freakclaw",
    "link": "https://www.ptt.cc/bbs/Gossiping/M.1641879056.A.F4F.html",
    "title": "[新聞] 老農津貼破兆 學者籲選舉產物落日"
  },
  {
    "author": "Emerson158",
    "link": "https://www.ptt.cc/bbs/Gossiping/M.1641879101.A.8E1.html",
    "title": "[問卦] 館長粉有哪些特徵？"
  },
  {
    "author": "zzzz8931",
    "link": "https://www.ptt.cc/bbs/Gossiping/M.1641879116.A.EC4.html",
    "title": "[問卦] 美國人有因為疫情就不約網友見面嗎？"
  },
  {
    "author": "seraphwind",
    "link": "https://www.ptt.cc/bbs/Gossiping/M.1641879120.A.71E.html",
    "title": "Re: [問卦] 美國真的醫療、警消系統面臨崩潰嗎？"
  },
  {
    "author": "breakofdawn",
    "link": "https://www.ptt.cc/bbs/Gossiping/M.1641879123.A.231.html",
    "title": "[新聞] 實質薪資衰退 近五年首見"
  },
  {
    "author": "hanlovangel",
    "link": "https://www.ptt.cc/bbs/Gossiping/M.1641879141.A.B9C.html",
    "title": "[新聞] 《木曜4》合作2天王破局爆內幕！看不上1"
  },
  {
    "author": "Luwan",
    "link": "https://www.ptt.cc/bbs/Gossiping/M.1641879147.A.06D.html",
    "title": "[問卦] 從幾歲開始覺得酒不難喝?"
  },
  {
    "author": "HyperPoro",
    "link": "https://www.ptt.cc/bbs/Gossiping/M.1641879168.A.4D7.html",
    "title": "Re: [問卦] 文茜世界週報怎麼回事?"
  },
  {
    "author": "rocket101",
    "link": "https://www.ptt.cc/bbs/Gossiping/M.1641879197.A.7D8.html",
    "title": "[問卦] 國小數學 某國小月考考題求救"
  },
  {
    "author": "fatslave",
    "link": "https://www.ptt.cc/bbs/Gossiping/M.1641879228.A.8A2.html",
    "title": "[問卦] 沒規矩女店員就鞭打你的拉麵店？"
  },
  {
    "author": "Tapqou",
    "link": "https://www.ptt.cc/bbs/Gossiping/M.1641879234.A.46C.html",
    "title": "Re: [新聞] 快訊／國民黨前立委龐建國墜樓　當場死亡"
  },
  {
    "author": "metallican",
    "link": "https://www.ptt.cc/bbs/Gossiping/M.1641879257.A.D89.html",
    "title": "[問卦] 康納的喬登是真的怪咖嗎"
  },
  {
    "author": "gk1329",
    "link": "https://www.ptt.cc/bbs/Gossiping/M.1641879279.A.BDE.html",
    "title": "[問卦] 本來就不可能有公平正義吧"
  },
  {
    "author": "CPer",
    "link": "https://www.ptt.cc/bbs/Gossiping/M.1641879291.A.0D6.html",
    "title": "[新聞] 防毒軟體擅自支援挖礦且關不掉！「諾頓36"
  },
  {
    "author": "onetiger",
    "link": "https://www.ptt.cc/bbs/Gossiping/M.1641879299.A.BC2.html",
    "title": "Re: [問卦] 台灣拉麵店規則怎麼這麼多？"
  },
  {
    "author": "bebehome",
    "link": "https://www.ptt.cc/bbs/Gossiping/M.1641879346.A.694.html",
    "title": "Re: [問卦] 館長粉有哪些特徵？"
  },
  {
    "author": "chean1020",
    "link": "https://www.ptt.cc/bbs/Gossiping/M.1641879351.A.871.html",
    "title": "[問卦] 宏達電投機仔還在妄想上100嗎？"
  },
  {
    "author": "pshuang",
    "link": "https://www.ptt.cc/bbs/Gossiping/M.1641879392.A.1DE.html",
    "title": "Re: [新聞] 凌晨4點3度傳「不公不義台灣，我生不如"
  },
  {
    "author": "koj",
    "link": "https://www.ptt.cc/bbs/Gossiping/M.1641879411.A.8D7.html",
    "title": "[問卦] 現在去桃園看房子的人在想什麼"
  },
  {
    "author": "falomu",
    "link": "https://www.ptt.cc/bbs/Gossiping/M.1641878622.A.3AE.html",
    "title": "[新聞] 一家10口擠破屋遭蛇擾 遭爆存款「比上班族多」"
  },
  {
    "author": "ahodes",
    "link": "https://www.ptt.cc/bbs/Gossiping/M.1641878638.A.DDF.html",
    "title": "[問卦] 文茜世界週報怎麼回事?"
  },
  {
    "author": "gerychen",
    "link": "https://www.ptt.cc/bbs/Gossiping/M.1641878647.A.CDD.html",
    "title": "[問卦] 自己的家都不能抽菸，菸蟲還有尊嚴嗎？"
  },
  {
    "author": "a8311700",
    "link": "https://www.ptt.cc/bbs/Gossiping/M.1641878654.A.592.html",
    "title": "[新聞] 好可愛！林靜儀揮「貓掌」謝票"
  },
  {
    "author": "zxc2331189",
    "link": "https://www.ptt.cc/bbs/Gossiping/M.1641878684.A.F31.html",
    "title": "[問卦] 震撼彈!! 尿出來的水柱竟然會旋轉?"
  },
  {
    "author": "eeee5566",
    "link": "https://www.ptt.cc/bbs/Gossiping/M.1641878719.A.C7D.html",
    "title": "Re: [新聞] 想不通！堅持「低消1杯飲料」惹火作家"
  },
  {
    "author": "saufu08",
    "link": "https://www.ptt.cc/bbs/Gossiping/M.1641878735.A.9AE.html",
    "title": "[問卦] 為何外籍肯做台灣人不想做的勞累髒工作呢"
  },
  {
    "author": "salu005",
    "link": "https://www.ptt.cc/bbs/Gossiping/M.1641878745.A.95A.html",
    "title": "[問卦] 張庭1300億，可算是娛樂圈最頂？"
  },
  {
    "author": "a55446262",
    "link": "https://www.ptt.cc/bbs/Gossiping/M.1641878755.A.5D2.html",
    "title": "[問卦] 期末考完晚餐吃什麼"
  },
  {
    "author": "bleach2009",
    "link": "https://www.ptt.cc/bbs/Gossiping/M.1641878774.A.4CE.html",
    "title": "[新聞] 外交部：確認高端已被泰國列入認可疫苗"
  },
  {
    "author": "vajra0001",
    "link": "https://www.ptt.cc/bbs/Gossiping/M.1641878805.A.BA4.html",
    "title": "Re: [新聞] 快訊／國民黨前立委龐建國墜樓　當場死亡"
  },
  {
    "author": "Kuru991",
    "link": "https://www.ptt.cc/bbs/Gossiping/M.1641878821.A.20D.html",
    "title": "[問卦] 女生說職業是小模，可以交往嗎？"
  },
  {
    "author": "a6234709",
    "link": "https://www.ptt.cc/bbs/Gossiping/M.1641878838.A.188.html",
    "title": "[問卦] 為何有人不喜歡嘻嘻"
  },
  {
    "author": "morgankhs",
    "link": "https://www.ptt.cc/bbs/Gossiping/M.1641878861.A.147.html",
    "title": "[問卦] 政府打房能解決生育率的低迷嗎？"
  },
  {
    "author": "takuminauki",
    "link": "https://www.ptt.cc/bbs/Gossiping/M.1641878914.A.DC2.html",
    "title": "[問卦] 念台大跟私大都一樣的八卦嗎?"
  },
  {
    "author": "TPAsavelove",
    "link": "https://www.ptt.cc/bbs/Gossiping/M.1641878939.A.BD1.html",
    "title": "Re: [新聞] 年輕人穿單薄衣物元旦衝武嶺　母急求救！"
  },
  {
    "author": "Arim",
    "link": "https://www.ptt.cc/bbs/Gossiping/M.1641878953.A.45D.html",
    "title": "[問卦] 雷根為什麼這麼屌"
  },
  {
    "author": "-",
    "link": "https://www.ptt.cc/bbs/Gossiping/M.1641878953.A.45D.html",
    "title": "(本文已被刪除) [beerme]"
  },
  {
    "author": "Lailungsheng",
    "link": "https://www.ptt.cc/bbs/Gossiping/M.1641878958.A.92D.html",
    "title": "Re: [新聞] 快訊／國民黨前立委龐建國墜樓　當場死亡"
  },
  {
    "author": "palindromes",
    "link": "https://www.ptt.cc/bbs/Gossiping/M.1641878991.A.351.html",
    "title": "[問卦] 有羨慕外勞又羨慕小黃司機的八卦嗎？"
  },
  {
    "author": "anbaow",
    "link": "https://www.ptt.cc/bbs/Gossiping/M.1641878008.A.397.html",
    "title": "[新聞] 鬆口氣 確診童跨年遊高雄 陳其邁：應是回"
  },
  {
    "author": "FacialHairTz",
    "link": "https://www.ptt.cc/bbs/Gossiping/M.1641878023.A.70D.html",
    "title": "[問卦] 機器沖的咖啡跟人用手沖的咖啡 差別是？"
  },
  {
    "author": "GivemeApen",
    "link": "https://www.ptt.cc/bbs/Gossiping/M.1641878028.A.FEE.html",
    "title": "Re: [問卦] 影片出租店的活路在哪裡"
  },
  {
    "author": "MrTaxes",
    "link": "https://www.ptt.cc/bbs/Gossiping/M.1641878046.A.FCB.html",
    "title": "Re: [新聞] 快訊／國民黨前立委龐建國墜樓　當場死亡"
  },
  {
    "author": "int1000",
    "link": "https://www.ptt.cc/bbs/Gossiping/M.1641878091.A.FBC.html",
    "title": "[問卦] 台男是不是也需要有男權團體"
  },
  {
    "author": "mjh",
    "link": "https://www.ptt.cc/bbs/Gossiping/M.1641878101.A.129.html",
    "title": "Re: [問卦] 為什麼台灣人不算中國人？"
  },
  {
    "author": "makinoyui",
    "link": "https://www.ptt.cc/bbs/Gossiping/M.1641878127.A.4F6.html",
    "title": "[問卦] 111111 不可能被亂噓叭？"
  },
  {
    "author": "bluekai22",
    "link": "https://www.ptt.cc/bbs/Gossiping/M.1641878152.A.31F.html",
    "title": "[新聞] 落地採檢考驗醫療量能 侯友宜：輕重症分"
  },
  {
    "author": "cyber0305",
    "link": "https://www.ptt.cc/bbs/Gossiping/M.1641878156.A.0F1.html",
    "title": "Re: [新聞] 想不通！堅持「低消1杯飲料」惹火作家"
  },
  {
    "author": "knight45683",
    "link": "https://www.ptt.cc/bbs/Gossiping/M.1641878167.A.DB2.html",
    "title": "[問卦] 為什麼是一直補助小黃啊"
  },
  {
    "author": "RLAPH",
    "link": "https://www.ptt.cc/bbs/Gossiping/M.1641878267.A.D5E.html",
    "title": "[問卦] 高中畢旅跟女生睡很正常吧"
  },
  {
    "author": "doomdied",
    "link": "https://www.ptt.cc/bbs/Gossiping/M.1641878280.A.FBB.html",
    "title": "Re: [問卦] 美國真的醫療、警消系統面臨崩潰嗎？"
  },
  {
    "author": "Win7",
    "link": "https://www.ptt.cc/bbs/Gossiping/M.1641878291.A.138.html",
    "title": "Re: [問卦] 台灣拉麵店規則怎麼這麼多？"
  },
  {
    "author": "fur",
    "link": "https://www.ptt.cc/bbs/Gossiping/M.1641878369.A.F98.html",
    "title": "[問卦] 有沒有這麼冷的天國中男生還穿短褲的八卦"
  },
  {
    "author": "moshenisshit",
    "link": "https://www.ptt.cc/bbs/Gossiping/M.1641878413.A.7B0.html",
    "title": "[問卦] 女生伸手借東西卻誤以為要牽手會怎樣？"
  },
  {
    "author": "BigMacGCB",
    "link": "https://www.ptt.cc/bbs/Gossiping/M.1641878444.A.2EE.html",
    "title": "[問卦] 有沒有優木いおり(優木伊織)的八卦"
  },
  {
    "author": "pttsuck5566",
    "link": "https://www.ptt.cc/bbs/Gossiping/M.1641878470.A.9E1.html",
    "title": "Re: [問卦] 牙齒黃了還有辦法洗白嗎？"
  },
  {
    "author": "aabbcc520",
    "link": "https://www.ptt.cc/bbs/Gossiping/M.1641878484.A.55F.html",
    "title": "[問卦] 今天的股市是嚇你甩你磨你嗎"
  },
  {
    "author": "bodhi",
    "link": "https://www.ptt.cc/bbs/Gossiping/M.1641878538.A.E38.html",
    "title": "[問卦] 這次疫情的破口在哪? 終於出現了嗎?"
  },
  {
    "author": "yi0116",
    "link": "https://www.ptt.cc/bbs/Gossiping/M.1641878575.A.8ED.html",
    "title": "[問卦] 台女愛uniqlo但不愛NET衣服"
  },
  {
    "author": "almanac",
    "link": "https://www.ptt.cc/bbs/Gossiping/M.1641877458.A.DBF.html",
    "title": "[問卦] 有沒有竹北遠百吃到飽網站被癱瘓的掛？"
  },
  {
    "author": "purue",
    "link": "https://www.ptt.cc/bbs/Gossiping/M.1641877472.A.AAC.html",
    "title": "[問卦] 近捷運房跟遠捷運加養車誰比較划"
  },
  {
    "author": "gk1329",
    "link": "https://www.ptt.cc/bbs/Gossiping/M.1641877489.A.0A9.html",
    "title": "Re: [問卦] 10年後有可能出生人數每年不到10萬嗎?"
  },
  {
    "author": "Gary9163",
    "link": "https://www.ptt.cc/bbs/Gossiping/M.1641877505.A.53E.html",
    "title": "[問卦] 騎車不戴手套一手插口袋一手握龍頭"
  },
  {
    "author": "jganet",
    "link": "https://www.ptt.cc/bbs/Gossiping/M.1641877580.A.51F.html",
    "title": "Re: [新聞] 莊瑞雄轟潘孟安「手握權力要節制」喊話"
  },
  {
    "author": "stevencool",
    "link": "https://www.ptt.cc/bbs/Gossiping/M.1641877607.A.54A.html",
    "title": "[新聞] 周春米宣布選屏東縣長 莊瑞雄：別跟國民"
  },
  {
    "author": "mikemagic88",
    "link": "https://www.ptt.cc/bbs/Gossiping/M.1641877608.A.171.html",
    "title": "Re: [問卦] 鄉民年輕時，都沒做過瘋狂的事情喔？"
  },
  {
    "author": "miimii24",
    "link": "https://www.ptt.cc/bbs/Gossiping/M.1641877621.A.4F5.html",
    "title": "[問卦] 婚姻版突然討論起過年雙方包紅包？"
  },
  {
    "author": "kumori",
    "link": "https://www.ptt.cc/bbs/Gossiping/M.1641877622.A.F4E.html",
    "title": "[問卦] 有酒空在店裡抽菸要怎麼趕走"
  },
  {
    "author": "yoyodiy",
    "link": "https://www.ptt.cc/bbs/Gossiping/M.1641877630.A.61A.html",
    "title": "[問卦] 山上下雪惹嗎？  台灣雪線多高?"
  },
  {
    "author": "PeterIsDog",
    "link": "https://www.ptt.cc/bbs/Gossiping/M.1641877643.A.362.html",
    "title": "[問卦] 慟！必勝客墨魚燉飯沒了！"
  },
  {
    "author": "affluent",
    "link": "https://www.ptt.cc/bbs/Gossiping/M.1641877651.A.050.html",
    "title": "Re: [新聞] 年輕人穿單薄衣物元旦衝武嶺　母急求救！"
  },
  {
    "author": "Fine29",
    "link": "https://www.ptt.cc/bbs/Gossiping/M.1641877685.A.D9D.html",
    "title": "[問卦] 從奶蓋X茶的奶蓋幾公分看店家氣度"
  },
  {
    "author": "v303v191",
    "link": "https://www.ptt.cc/bbs/Gossiping/M.1641877698.A.5E3.html",
    "title": "[問卦] 早上洗頭 晚上洗頭 都幾"
  },
  {
    "author": "not5not6not7",
    "link": "https://www.ptt.cc/bbs/Gossiping/M.1641877710.A.59E.html",
    "title": "[問卦] 貓貓這樣是不是對我示愛"
  },
  {
    "author": "E24056823",
    "link": "https://www.ptt.cc/bbs/Gossiping/M.1641877726.A.15E.html",
    "title": "Re: [新聞] 快訊／國民黨前立委龐建國墜樓　當場死亡"
  },
  {
    "author": "ai770116",
    "link": "https://www.ptt.cc/bbs/Gossiping/M.1641877798.A.D11.html",
    "title": "[問卦] 要服務業加薪是不是想害死台灣？"
  },
  {
    "author": "butten986",
    "link": "https://www.ptt.cc/bbs/Gossiping/M.1641877844.A.3B9.html",
    "title": "Re: [問卦] 10年後有可能出生人數每年不到10萬嗎?"
  },
  {
    "author": "owo0204",
    "link": "https://www.ptt.cc/bbs/Gossiping/M.1641877920.A.0F0.html",
    "title": "[問卦] 那種會做危險蠢事的人往往都有女友？"
  },
  {
    "author": "ffreakk",
    "link": "https://www.ptt.cc/bbs/Gossiping/M.1641877939.A.1F1.html",
    "title": "[新聞] 疫情燒進台北市！薑母鴨店「有確診者足"
  },
  {
    "author": "syearth",
    "link": "https://www.ptt.cc/bbs/Gossiping/M.1641876688.A.913.html",
    "title": "[問卦] 移工變移民 包租公、婆會不會一堆東南亞?"
  },
  {
    "author": "dinhan",
    "link": "https://www.ptt.cc/bbs/Gossiping/M.1641876723.A.F2C.html",
    "title": "[問卦] 台北市古亭這樣130貴嗎？"
  },
  {
    "author": "AtenWang",
    "link": "https://www.ptt.cc/bbs/Gossiping/M.1641876763.A.115.html",
    "title": "[問卦] 這個社會是不是對一般人很很不公平？"
  },
  {
    "author": "sven1130",
    "link": "https://www.ptt.cc/bbs/Gossiping/M.1641876763.A.85F.html",
    "title": "Re: [新聞] 想不通！堅持「低消1杯飲料」惹火作家"
  },
  {
    "author": "BigBird56",
    "link": "https://www.ptt.cc/bbs/Gossiping/M.1641876779.A.DD0.html",
    "title": "[問卦] 給老闆一個加薪的理由"
  },
  {
    "author": "P0GUY",
    "link": "https://www.ptt.cc/bbs/Gossiping/M.1641876825.A.F06.html",
    "title": "Re: [新聞] 凌晨4點3度傳「不公不義台灣，我生不如"
  },
  {
    "author": "brucesuperQ",
    "link": "https://www.ptt.cc/bbs/Gossiping/M.1641876854.A.C91.html",
    "title": "[新聞] 防疫計程車補貼每天3500元 禁載一般客"
  },
  {
    "author": "kprc",
    "link": "https://www.ptt.cc/bbs/Gossiping/M.1641876950.A.5C3.html",
    "title": "[問卦] 星巴克的杯蓋居然可以旋轉"
  },
  {
    "author": "rz2x",
    "link": "https://www.ptt.cc/bbs/Gossiping/M.1641877071.A.D56.html",
    "title": "Re: [問卦] 新郎看到伴娘奶超大的時候在想什麼？"
  },
  {
    "author": "LOXA0115",
    "link": "https://www.ptt.cc/bbs/Gossiping/M.1641877076.A.803.html",
    "title": "[新聞] 野獸回歸？網友瘋傳 Toyz 夜店放風影片"
  },
  {
    "author": "freertos",
    "link": "https://www.ptt.cc/bbs/Gossiping/M.1641877115.A.7BE.html",
    "title": "[問卦] 如果遲早會感染. 規劃好分批感染 OK? =^="
  },
  {
    "author": "xa9277178",
    "link": "https://www.ptt.cc/bbs/Gossiping/M.1641877209.A.A7F.html",
    "title": "Re: [新聞] 房價飆年輕人「買不起雙北」 內行掀數據"
  },
  {
    "author": "TaraSoYeon",
    "link": "https://www.ptt.cc/bbs/Gossiping/M.1641877224.A.5F0.html",
    "title": "[問卦] 我想當台灣的總統第一步要學會什麼技能？"
  },
  {
    "author": "Beethoven",
    "link": "https://www.ptt.cc/bbs/Gossiping/M.1641877232.A.92A.html",
    "title": "[問卦] 印度阿三的英文口音是不是一絕"
  },
  {
    "author": "yokann",
    "link": "https://www.ptt.cc/bbs/Gossiping/M.1641877262.A.32D.html",
    "title": "[問卦] Ptt歐兔版的陽氣有多重？"
  },
  {
    "author": "ccf52881",
    "link": "https://www.ptt.cc/bbs/Gossiping/M.1641877274.A.E17.html",
    "title": "[新聞] 溫朗東掀包裝：陳玉珍不是女版顏寬恒，"
  },
  {
    "author": "Tsumugifans",
    "link": "https://www.ptt.cc/bbs/Gossiping/M.1641877362.A.A4E.html",
    "title": "[新聞] 1922疫苗預約平台1/15重新開放 台中市規"
  },
  {
    "author": "LaAc",
    "link": "https://www.ptt.cc/bbs/Gossiping/M.1641877388.A.8A3.html",
    "title": "[問卦] 影片出租店的活路在哪裡"
  },
  {
    "author": "pchunters",
    "link": "https://www.ptt.cc/bbs/Gossiping/M.1641877443.A.36D.html",
    "title": "[問卦] 鄉民年輕時，都沒做過瘋狂的事情喔？"
  },
  {
    "author": "KanzakiHAria",
    "link": "https://www.ptt.cc/bbs/Gossiping/M.1641877449.A.CC0.html",
    "title": "[問卦] 有人買Disney+給父母看的嗎?"
  },
  {
    "author": "karl085",
    "link": "https://www.ptt.cc/bbs/Gossiping/M.1641876007.A.085.html",
    "title": "[新聞] 丁渝洲：世界上沒有永久的朋友 台灣不能"
  },
  {
    "author": "allenduncan",
    "link": "https://www.ptt.cc/bbs/Gossiping/M.1641876057.A.ED9.html",
    "title": "[新聞] 加倍的愛／妻車禍亡留兩幼子　他忍淚父代"
  },
  {
    "author": "slycsboy",
    "link": "https://www.ptt.cc/bbs/Gossiping/M.1641876062.A.1FB.html",
    "title": "Re: [問卦] 今天交通部好熱鬧，有卦嗎？"
  },
  {
    "author": "MrTaxes",
    "link": "https://www.ptt.cc/bbs/Gossiping/M.1641876068.A.33F.html",
    "title": "[問卦] 官員弟猥褻女童減刑兩次,聲請再審拚無罪?"
  },
  {
    "author": "s386644187",
    "link": "https://www.ptt.cc/bbs/Gossiping/M.1641876086.A.5EA.html",
    "title": "[問卦] 食神大賽哪道做出來最好吃？"
  },
  {
    "author": "hatephubbing",
    "link": "https://www.ptt.cc/bbs/Gossiping/M.1641876090.A.67B.html",
    "title": "[問卦] 在山上聽鬼故事突然停電怎辦？"
  },
  {
    "author": "nges10310",
    "link": "https://www.ptt.cc/bbs/Gossiping/M.1641876139.A.0F8.html",
    "title": "Re: [爆卦] 桃園案17505在高雄足跡"
  },
  {
    "author": "kawazakiz2",
    "link": "https://www.ptt.cc/bbs/Gossiping/M.1641876190.A.1AA.html",
    "title": "Re: [新聞] 年輕人穿單薄衣物元旦衝武嶺　母急求救！"
  },
  {
    "author": "zalora",
    "link": "https://www.ptt.cc/bbs/Gossiping/M.1641876285.A.D1A.html",
    "title": "[問卦] 有沒有中國嚴重空污正要入侵台灣的八卦?"
  },
  {
    "author": "MoneyMonkey",
    "link": "https://www.ptt.cc/bbs/Gossiping/M.1641876333.A.A84.html",
    "title": "Re: [問卦] 美國真的醫療、警消系統面臨崩潰嗎？"
  },
  {
    "author": "MiCy",
    "link": "https://www.ptt.cc/bbs/Gossiping/M.1641876438.A.A08.html",
    "title": "[問卦] 有「東」字的自營早餐店名該怎麼取？"
  },
  {
    "author": "iamgaylan",
    "link": "https://www.ptt.cc/bbs/Gossiping/M.1641876456.A.D66.html",
    "title": "[問卦] 台灣高中制服為啥沒窄裙？"
  },
  {
    "author": "KanzakiHAria",
    "link": "https://www.ptt.cc/bbs/Gossiping/M.1641876497.A.4F2.html",
    "title": "[問卦] 我爸媽整天都在看TVBS新聞台"
  },
  {
    "author": "Daniel0712",
    "link": "https://www.ptt.cc/bbs/Gossiping/M.1641876508.A.B70.html",
    "title": "[問卦] 薯條加進玉米濃湯是不是最讚？"
  },
  {
    "author": "bryant70176",
    "link": "https://www.ptt.cc/bbs/Gossiping/M.1641876605.A.81B.html",
    "title": "[問卦] 慟！確診者和大家吸同樣的空氣！"
  },
  {
    "author": "mikemagic88",
    "link": "https://www.ptt.cc/bbs/Gossiping/M.1641876628.A.C3C.html",
    "title": "Re: [新聞] 年輕人穿單薄衣物元旦衝武嶺　母急求救！"
  },
  {
    "author": "school5566",
    "link": "https://www.ptt.cc/bbs/Gossiping/M.1641876636.A.F66.html",
    "title": "[問卦] 百年後世界只剩東南亞跟黑人跟穆斯林嗎？"
  },
  {
    "author": "extremevs",
    "link": "https://www.ptt.cc/bbs/Gossiping/M.1641876659.A.A02.html",
    "title": "[問卦] 從幾歲開始覺得咖啡不難喝的？"
  },
  {
    "author": "yvefly",
    "link": "https://www.ptt.cc/bbs/Gossiping/M.1641876673.A.252.html",
    "title": "[新聞] 中興醫院傳醫護確診 北市聯醫：待中央公"
  },
  {
    "author": "xcitboy",
    "link": "https://www.ptt.cc/bbs/Gossiping/M.1641876680.A.900.html",
    "title": "[問卦] 有沒有在學校挖礦的八卦"
  },
  {
    "author": "devidevi",
    "link": "https://www.ptt.cc/bbs/Gossiping/M.1641875325.A.275.html",
    "title": "Re: [新聞] 兩周3件泰郵包含非洲豬瘟肉品 蘇貞昌要求"
  },
  {
    "author": "girl55665566",
    "link": "https://www.ptt.cc/bbs/Gossiping/M.1641875370.A.819.html",
    "title": "[新聞] 狼師拐簽「絕對服從契約」猥褻5男生判刑"
  },
  {
    "author": "hito0509",
    "link": "https://www.ptt.cc/bbs/Gossiping/M.1641875381.A.7A1.html",
    "title": "[新聞] 年輕人穿單薄衣物元旦衝武嶺　母急求救！"
  },
  {
    "author": "abcrr123",
    "link": "https://www.ptt.cc/bbs/Gossiping/M.1641875404.A.143.html",
    "title": "[問卦] 牙齒黃了還有辦法洗白嗎？"
  },
  {
    "author": "Articuno",
    "link": "https://www.ptt.cc/bbs/Gossiping/M.1641875454.A.C5B.html",
    "title": "[新聞] 憂換鈔群聚 中央銀行倡數位紅包"
  },
  {
    "author": "TyuzuChou",
    "link": "https://www.ptt.cc/bbs/Gossiping/M.1641875473.A.074.html",
    "title": "[問卦] 蛋黃區蛋白區蛋殼區怎麼分"
  },
  {
    "author": "yaoniy",
    "link": "https://www.ptt.cc/bbs/Gossiping/M.1641875552.A.D22.html",
    "title": "[新聞] 民憂打不到第三劑 侯友宜：盼中央快速補"
  },
  {
    "author": "ray90910",
    "link": "https://www.ptt.cc/bbs/Gossiping/M.1641875561.A.DDE.html",
    "title": "Re: [問卦] 茶金的宣傳是怎麼輸華燈初上的"
  },
  {
    "author": "NTU100",
    "link": "https://www.ptt.cc/bbs/Gossiping/M.1641875584.A.75D.html",
    "title": "Re: [問卦] 新郎看到伴娘奶超大的時候在想什麼？"
  },
  {
    "author": "leepingyo",
    "link": "https://www.ptt.cc/bbs/Gossiping/M.1641875610.A.DB0.html",
    "title": "[新聞] 【人民會不開心】新冠疫情衝擊財政　泰國"
  },
  {
    "author": "deeeplove",
    "link": "https://www.ptt.cc/bbs/Gossiping/M.1641875677.A.475.html",
    "title": "[新聞] 石原聰美報喜！宣布做人成功準備升格當"
  },
  {
    "author": "assassinASHE",
    "link": "https://www.ptt.cc/bbs/Gossiping/M.1641875718.A.E59.html",
    "title": "Re: [新聞] 狼師拐簽「絕對服從契約」猥褻5男生判刑"
  },
  {
    "author": "cutiehoneyzu",
    "link": "https://www.ptt.cc/bbs/Gossiping/M.1641875731.A.1CA.html",
    "title": "Re: [爆卦] 桃園案17505在高雄足跡"
  },
  {
    "author": "-",
    "link": "https://www.ptt.cc/bbs/Gossiping/M.1641875731.A.1CA.html",
    "title": "(本文已被刪除) [sinksink]"
  },
  {
    "author": "kk0521kk",
    "link": "https://www.ptt.cc/bbs/Gossiping/M.1641875802.A.C82.html",
    "title": "[問卦] 台北CP值超高自助餐"
  },
  {
    "author": "oylq2000",
    "link": "https://www.ptt.cc/bbs/Gossiping/M.1641875805.A.02C.html",
    "title": "[問卦] 有沒有電影配音超級假的八卦？"
  },
  {
    "author": "brbear",
    "link": "https://www.ptt.cc/bbs/Gossiping/M.1641875814.A.280.html",
    "title": "[問卦] 台灣的客家人很團結 閩南人四分五裂"
  },
  {
    "author": "lovek123",
    "link": "https://www.ptt.cc/bbs/Gossiping/M.1641875831.A.C6F.html",
    "title": "Re: [新聞] 「完全尊重民主」　顏寬恒深夜400字心聲"
  },
  {
    "author": "PowerChip",
    "link": "https://www.ptt.cc/bbs/Gossiping/M.1641875979.A.F46.html",
    "title": "[問卦] 為什麼人類要汙名化一些自然的事情"
  },
  {
    "author": "bodhi",
    "link": "https://www.ptt.cc/bbs/Gossiping/M.1641875997.A.CBE.html",
    "title": "Re: [新聞] 凌晨4點3度傳「不公不義台灣，我生不如"
  },
  {
    "author": "coeXist",
    "link": "https://www.ptt.cc/bbs/Gossiping/M.1641875035.A.7F7.html",
    "title": "Re: [問卦] 新郎看到伴娘奶超大的時候在想什麼？"
  },
  {
    "author": "f12sd2e2aa",
    "link": "https://www.ptt.cc/bbs/Gossiping/M.1641875036.A.E45.html",
    "title": "[問卦] 台積電作業員怎麼不罷工要求加薪？"
  },
  {
    "author": "Sonia1022",
    "link": "https://www.ptt.cc/bbs/Gossiping/M.1641875138.A.223.html",
    "title": "[新聞] 龐建國驚傳已罹癌　凌晨傳「12字尋死訊"
  },
  {
    "author": "kemal969",
    "link": "https://www.ptt.cc/bbs/Gossiping/M.1641875140.A.BF4.html",
    "title": "[問卦] 10年後有可能出生人數每年不到10萬嗎?"
  },
  {
    "author": "skyoun",
    "link": "https://www.ptt.cc/bbs/Gossiping/M.1641875178.A.488.html",
    "title": "Re: [新聞] 張庭林瑞陽完了！陸官方震怒「出動400官"
  },
  {
    "author": "cowardlyman",
    "link": "https://www.ptt.cc/bbs/Gossiping/M.1641875178.A.850.html",
    "title": "[問卦] 不破聖衣來3分速跑完10km，什麼概念？"
  },
  {
    "author": "medama",
    "link": "https://www.ptt.cc/bbs/Gossiping/M.1641875198.A.8F0.html",
    "title": "[新聞] 每3天就1童誤食毒物　17歲少年喝到阿嬤"
  },
  {
    "author": "-",
    "link": "https://www.ptt.cc/bbs/Gossiping/M.1641875198.A.8F0.html",
    "title": "(本文已被刪除) [motan]"
  },
  {
    "author": "brbear",
    "link": "https://www.ptt.cc/bbs/Gossiping/M.1641875218.A.81B.html",
    "title": "[問卦] 荷蘭紅毛會被閩南人趕出台灣？"
  },
  {
    "author": "taot917",
    "link": "https://www.ptt.cc/bbs/Gossiping/M.1641875224.A.60C.html",
    "title": "[問卦] 韭菜的薪資，有必要操老闆的心嗎？"
  },
  {
    "author": "nicolaschen2",
    "link": "https://www.ptt.cc/bbs/Gossiping/M.1641875225.A.4D0.html",
    "title": "Re: [問卦] 小六數學題 難倒 大學生?"
  },
  {
    "author": "SSglamr",
    "link": "https://www.ptt.cc/bbs/Gossiping/M.1641875246.A.025.html",
    "title": "Re: [問卦] 匿名攻擊同業的人很多嗎"
  },
  {
    "author": "Conan5566",
    "link": "https://www.ptt.cc/bbs/Gossiping/M.1641875252.A.A49.html",
    "title": "[問卦] 馬雲會跟林瑞陽夫妻說什麼？"
  },
  {
    "author": "-",
    "link": "https://www.ptt.cc/bbs/Gossiping/M.1641875252.A.A49.html",
    "title": "(本文已被刪除) [traman]"
  },
  {
    "author": "caeasonfb",
    "link": "https://www.ptt.cc/bbs/Gossiping/M.1641875273.A.11D.html",
    "title": "Re: [問卦] 美國真的醫療、警消系統面臨崩潰嗎？"
  },
  {
    "author": "coober",
    "link": "https://www.ptt.cc/bbs/Gossiping/M.1641875277.A.FC8.html",
    "title": "Re: [新聞] 快訊／國民黨前立委龐建國墜樓　當場死亡"
  },
  {
    "author": "a326516",
    "link": "https://www.ptt.cc/bbs/Gossiping/M.1641875292.A.911.html",
    "title": "[新聞] 莊瑞雄轟潘孟安「手握權力要節制」喊話"
  },
  {
    "author": "CHealth",
    "link": "https://www.ptt.cc/bbs/Gossiping/M.1641875296.A.282.html",
    "title": "Re: [新聞] 無懼疫情 王品去年營收171.5億元創歷史新"
  },
  {
    "author": "kkk1234",
    "link": "https://www.ptt.cc/bbs/Gossiping/M.1641875297.A.101.html",
    "title": "[問卦] 什麼是人類圖？"
  },
  {
    "author": "bornwinner",
    "link": "https://www.ptt.cc/bbs/Gossiping/M.1641875313.A.2F6.html",
    "title": "[問卦] 台灣拉麵店規則怎麼這麼多？"
  }
]